{"cameraMode":{"drawMode":31,"name":"Sprite Mask","section":"Miscellaneous"},"sceneLighting":false,"audioPlay":false,"sceneViewState":{"m_AlwaysRefresh":false,"showFog":true,"showSkybox":false,"showFlares":true,"showImageEffects":true,"showParticleSystems":true,"showVisualEffectGraphs":true,"m_FxEnabled":true},"in2DMode":false,"pivot":{"x":371.5,"y":663.5,"z":0.0},"rotation":{"x":-0.06617801636457443,"y":0.9322487711906433,"z":-0.27800196409225466,"w":-0.22192071378231049},"size":769.9879760742188,"orthographic":false}